setup.cfg
setup.py
./Talker.py
./__init__.py
./catalogs.py
./cmaps.py
./color.py
./finder.py
./iplot.py
./oned.py
./painting.py
./read.py
./slit_mask_regions.py
./spherical.py
./star.py
./stats.py
./strings.py
./twod.py
./units.py
./utils.py
borrowed/__init__.py
borrowed/crossfield.py
displays/Display.py
displays/__init__.py
displays/ds9.py
displays/imshow.py
displays/movie.py
displays/regions.py
relations/Covey.py
relations/Davenport.py
relations/Mamajek.py
relations/Relation.py
relations/__init__.py
zachopy.egg-info/PKG-INFO
zachopy.egg-info/SOURCES.txt
zachopy.egg-info/dependency_links.txt
zachopy.egg-info/requires.txt
zachopy.egg-info/top_level.txt