Metadata-Version: 1.1
Name: zachopy
Version: 0.1.4
Summary: Various tools used in lots of code written by Zach Berta-Thompson (zkbt@mit.edu)
Home-page: https://github.com/TESScience/zachopy
Author: Zach Berta-Thompson
Author-email: zkbt@mit.edu
License: UNKNOWN
Download-URL: https://github.com/TESScience/zachopy/tarball/0.1.4
Platform: UNKNOWN
